medux/common/__init__.py
medux/common/admin.py
medux/common/apps.py
medux/common/bootstrap.py
medux/common/conf.py
medux/common/constants.py
medux/common/context_processors.py
medux/common/menu.py
medux/common/menus.py
medux/common/middleware.py
medux/common/mixins.py
medux/common/models.py
medux/common/signals.py
medux/common/tools.py
medux/common/urls.py
medux/common/validators.py
medux/common/widgets.py
medux/common/api/__init__.py
medux/common/api/interfaces.py
medux/common/api/http/__init__.py
medux/common/auth/__init__.py
medux/common/auth/forms.py
medux/common/forms/__init__.py
medux/common/forms/mixins.py
medux/common/forms/user.py
medux/common/forms/widgets.py
medux/common/htmx/__init__.py
medux/common/htmx/mixins.py
medux/common/locale/de/LC_MESSAGES/django.mo
medux/common/locale/de/LC_MESSAGES/django.po
medux/common/management/__init__.py
medux/common/management/commands/__init__.py
medux/common/management/commands/initialize.py
medux/common/management/commands/loadpreferences.py
medux/common/management/commands/update_libraries.py
medux/common/migrations/0001_initial.py
medux/common/migrations/__init__.py
medux/common/static/common/.gitkeep
medux/common/static/common/css/bootstrap-icons.css
medux/common/static/common/css/medux_common.css
medux/common/static/common/css/tabler.css
medux/common/static/common/css/fonts/bootstrap-icons.woff
medux/common/static/common/css/fonts/bootstrap-icons.woff2
medux/common/static/common/js/Sortable.min.js
medux/common/static/common/js/medux_common.js
medux/common/static/common/js/tabler.js
medux/common/static/common/js/toasts.js
medux/common/static/common/js/htmx/htmx.js
medux/common/static/common/js/htmx/htmx.min.js
medux/common/static/common/js/htmx/ext/debug.js
medux/common/static/common/js/htmx/ext/ws.js
medux/common/templates/bootstrap5/layout/card.html
medux/common/templates/bootstrap5/layout/color_input.html
medux/common/templates/bootstrap5/layout/modal.html
medux_common-0.0.7.dist-info/DESCRIPTION.rst
medux_common-0.0.7.dist-info/METADATA
medux_common-0.0.7.dist-info/RECORD
medux_common-0.0.7.dist-info/WHEEL
medux_common-0.0.7.dist-info/entry_points.txt
medux_common-0.0.7.dist-info/metadata.json
medux_common-0.0.7.dist-info/top_level.txt
