Metadata-Version: 2.0
Name: medux-common
Version: 0.0.7
Summary: Common functionality for MedUX / MedUX Online
Author-email: Christian González <christian.gonzalez@nerdocs.at>
Project-URL: Source, https://gitlab.com/nerdocs/medux/medux-common
Project-URL: Tracker, https://gitlab.com/nerdocs/medux/medux-common/-/issues
Classifier: License :: OSI Approved :: GNU Affero General Public License v3 or later (AGPLv3+)
Requires-Dist: django[argon2] (~=4.1)
Requires-Dist: gdaps (>=0.6.4)
Requires-Dist: django-crispy-forms
Requires-Dist: crispy-bootstrap5
Requires-Dist: phonenumbers
Requires-Dist: django-extra-views
Requires-Dist: django-htmx
Requires-Dist: django-environ
Requires-Dist: whitenoise
Requires-Dist: django-composite-field
Requires-Dist: channels (>=4.0.0)
Requires-Dist: daphne (>=4.0.0)
Requires-Dist: djangorestframework
Requires-Dist: toml
Requires-Dist: django-polymorphic
Requires-Dist: django-extensions
Requires-Dist: django-component-tags
Requires-Dist: django-money
Requires-Dist: django-colorfield
